{"Label": "215", "Id": "000", "Type": "DISCRETE", "9": {"IBit": 9, "FBit": 9, "Name": "FLIGHT(B0)", "Details": {"1": "", "0": "1"}}, "10": {"IBit": 10, "FBit": 10, "Name": "FLIGHT(B1)", "Details": {"1": "", "0": "2"}}, "11": {"IBit": 11, "FBit": 11, "Name": "FLIGHT(B2)", "Details": {"1": "", "0": "4"}}, "12": {"IBit": 12, "FBit": 12, "Name": "FLIGHT(B3)", "Details": {"1": "", "0": "8"}}, "13": {"IBit": 13, "FBit": 13, "Name": "FLIGHT(B4)", "Details": {"1": "", "0": "16"}}, "14": {"IBit": 14, "FBit": 14, "Name": "FLIGHT(B5)", "Details": {"1": "", "0": "32"}}, "15": {"IBit": 15, "FBit": 15, "Name": "COMM7(B0)", "Details": {"1": "", "0": "1"}}, "16": {"IBit": 16, "FBit": 16, "Name": "COMM7(B1)", "Details": {"1": "", "0": "2"}}, "17": {"IBit": 17, "FBit": 17, "Name": "COMM7(B2)", "Details": {"1": "", "0": "4"}}, "18": {"IBit": 18, "FBit": 18, "Name": "COMM7(B3)", "Details": {"1": "", "0": "8"}}, "19": {"IBit": 19, "FBit": 19, "Name": "COMM7(B4)", "Details": {"1": "", "0": "16"}}, "20": {"IBit": 20, "FBit": 20, "Name": "COMM7(B5)", "Details": {"1": "", "0": "32"}}, "21": {"IBit": 21, "FBit": 21, "Name": "CABIN(B0)", "Details": {"1": "", "0": "1"}}, "22": {"IBit": 22, "FBit": 22, "Name": "CABIN(B1)", "Details": {"1": "", "0": "2"}}, "23": {"IBit": 23, "FBit": 23, "Name": "CABIN(B2)", "Details": {"1": "", "0": "4"}}, "24": {"IBit": 24, "FBit": 24, "Name": "CABIN(B3)", "Details": {"1": "", "0": "8"}}, "25": {"IBit": 25, "FBit": 25, "Name": "CABIN(B4)", "Details": {"1": "", "0": "16"}}, "26": {"IBit": 26, "FBit": 26, "Name": "CABIN(B5)", "Details": {"1": "", "0": "32"}}}